m3/__init__.py
m3/caching.py
m3/finders.py
m3/metrics.py
m3/plugins.py
m3/actions/__init__.py
m3/actions/async.py
m3/actions/context.py
m3/actions/exceptions.py
m3/actions/interfaces.py
m3/actions/metrics.py
m3/actions/packs.py
m3/actions/results.py
m3/actions/tree_packs.py
m3/actions/urls.py
m3/actions/utils.py
m3/actions/dicts/__init__.py
m3/actions/dicts/simple.py
m3/actions/dicts/tree.py
m3/db/__init__.py
m3/db/mptt_util.py
m3/db/tools.py
m3/db/transaction_context.py
m3/management/__init__.py
m3/management/commands/__init__.py
m3/management/commands/selftest.py
m3/templatetags/__init__.py
m3/templatetags/m3_tags.py
m3_core-3.1.19.dist-info/LICENSE
m3_core-3.1.19.dist-info/METADATA
m3_core-3.1.19.dist-info/WHEEL
m3_core-3.1.19.dist-info/top_level.txt
m3_core-3.1.19.dist-info/RECORD
