Metadata-Version: 2.1
Name: m3-core
Version: 3.1.19
Summary: ## M3-Core
Home-page: https://github.com/barsgroup/m3-core
Author: BARS Group
Author-email: bars@bars-open.ru
License: MIT
Classifier: Intended Audience :: Developers
Classifier: Environment :: Web Environment
Classifier: Natural Language :: Russian
Classifier: Natural Language :: English
Classifier: Operating System :: OS Independent
Classifier: Programming Language :: Python
Classifier: License :: OSI Approved :: MIT License
Classifier: Development Status :: 5 - Production/Stable
License-File: LICENSE
Requires-Dist: m3-builder >=1.2.0
Requires-Dist: m3-django-compat >=1.5.1
